sublemon/__init__.py
sublemon/errors.py
sublemon/runtime.py
sublemon/subprocess.py
sublemon/utils.py
sublemon/version.py
sublemon-0.0.2.dist-info/LICENSE.txt
sublemon-0.0.2.dist-info/METADATA
sublemon-0.0.2.dist-info/WHEEL
sublemon-0.0.2.dist-info/top_level.txt
sublemon-0.0.2.dist-info/RECORD
