Metadata-Version: 2.1
Name: sublemon
Version: 0.0.2
Summary: Local asynchronous subprocess generation as a Python library
Home-page: https://github.com/welchbj/sublemon
Author: Brian Welch
Author-email: welch18@vt.edu
License: MIT
Platform: UNKNOWN
Classifier: Environment :: Console
Classifier: License :: OSI Approved :: MIT License
Classifier: Operating System :: MacOS :: MacOS X
Classifier: Operating System :: Microsoft :: Windows
Classifier: Operating System :: POSIX
Classifier: Programming Language :: Python :: 3.6
Classifier: Topic :: Utilities
Requires-Dist: aiostream
